elgoogapi/__init__.py
elgoogapi/auth/__init__.py
elgoogapi/auth/oauthlib/__init__.py
elgoogapi/auth/oauthlib/flow.py
elgoogapi-0.1.0.dist-info/METADATA
elgoogapi-0.1.0.dist-info/WHEEL
elgoogapi-0.1.0.dist-info/top_level.txt
elgoogapi-0.1.0.dist-info/RECORD
